tidues_tools/ConfParser.py
tidues_tools/GeneralMap.py
tidues_tools/GraphGen.py
tidues_tools/__init__.py
tidues_tools-0.2.0.dist-info/LICENSE
tidues_tools-0.2.0.dist-info/METADATA
tidues_tools-0.2.0.dist-info/WHEEL
tidues_tools-0.2.0.dist-info/top_level.txt
tidues_tools-0.2.0.dist-info/RECORD
